setup.py
geradorfdp/__init__.py
geradorfdp.egg-info/PKG-INFO
geradorfdp.egg-info/SOURCES.txt
geradorfdp.egg-info/dependency_links.txt
geradorfdp.egg-info/requires.txt
geradorfdp.egg-info/top_level.txt
scripts/fdp-gen