Metadata-Version: 1.0
Name: geradorfdp
Version: 0.1
Summary: Gerador de horários para Folha de Ponto
Home-page: https://github.com/daltonmatos/geradorfdp
Author: Dalton Barreto
Author-email: daltonmatos@gmail.com
License: GPLv2
Platform: UNKNOWN
Classifier: License :: OSI Approved :: GNU General Public License (GPL)
Classifier: Operating System :: OS Independent
Classifier: Programming Language :: Python
